deep_nlp_service/__init__.py
deep_nlp_service/config.py
deep_nlp_service/models/__init__.py
deep_nlp_service/models/attention.py
deep_nlp_service/models/bert_model.py
deep_nlp_service/models/dataset.py
deep_nlp_service/utils/__init__.py
deep_nlp_service/utils/data_processor.py
deep_nlp_service/utils/logger.py
SimsysDNLP-0.0.4.dist-info/METADATA
SimsysDNLP-0.0.4.dist-info/WHEEL
SimsysDNLP-0.0.4.dist-info/top_level.txt
SimsysDNLP-0.0.4.dist-info/RECORD
