Metadata-Version: 2.1
Name: SimsysDNLP
Version: 0.0.4
Summary: A deep learning natural language processing service for simulating different systems (normal-parallel-single server).
Home-page: https://github.com/Mohamed-Hamdey/DNLP-Simulation-Service
Author: Mohamed Hamdey
Author-email: mohamed.hamdey@gmail.com
Classifier: Programming Language :: Python :: 3
Classifier: License :: OSI Approved :: MIT License
Classifier: Operating System :: OS Independent
Requires-Python: >=3.6
Requires-Dist: torch
Requires-Dist: transformers
Requires-Dist: wandb
Requires-Dist: scikit-learn
Requires-Dist: numpy
